stocra/__init__.py
stocra/asynchronous/__init__.py
stocra/asynchronous/client.py
stocra/asynchronous/error_handlers.py
stocra/base_client.py
stocra/models.py
stocra/py.typed
stocra/synchronous/__init__.py
stocra/synchronous/client.py
stocra/synchronous/error_handlers.py
stocra/utils.py
stocra-1.0.0.dist-info/WHEEL
stocra-1.0.0.dist-info/METADATA
stocra-1.0.0.dist-info/RECORD
