Metadata-Version: 2.1
Name: stocra
Version: 1.0.0
Summary: Stocra.com python sdk
Home-page: https://stocra.com
License: MIT
Author: Lukáš Vokráčko
Author-email: lukas@vokracko.cz
Requires-Python: >=3.7,<4.0
Classifier: License :: OSI Approved :: MIT License
Classifier: Programming Language :: Python :: 3
Classifier: Programming Language :: Python :: 3.10
Classifier: Programming Language :: Python :: 3.7
Classifier: Programming Language :: Python :: 3.8
Classifier: Programming Language :: Python :: 3.9
Provides-Extra: asynchronous
Provides-Extra: synchronous
Requires-Dist: aiohttp; extra == "asynchronous"
Requires-Dist: pydantic
Requires-Dist: requests; extra == "synchronous"
Project-URL: Repository, https://github.com/stocra/sdk-python
